{
  "towers": [
    {
      "id": "militia",
      "tier": 1,
      "archetype": "close",
      "race": "iron-covenant",
      "unitType": "Militia",
      "range": 1.5,
      "damage": 20,
      "damageType": "physical",
      "defense": 4,
      "armorByType": {
        "physical": 4,
        "fire": 2,
        "water": 2,
        "earth": 3,
        "air": 2
      },
      "maxHealth": 200,
      "attacksPerSecond": 1,
      "color": "#6bcb77",
      "sizeScale": 0.7,
      "isMobile": false,
      "moveSpeedPerTick": 0,
      "goldValue": 25,
      "weaknesses": [],
      "skills": [],
      "kamikazeExplosionRadiusTiles": 0
    }
  ]
}
